{
	"info": {
		"_postman_id": "1f9a48e8-e1bf-41a8-9a0f-fe97c489c85e",
		"name": "Auth",
		"schema": "https://schema.getpostman.com/json/collection/v2.1.0/collection.json",
		"_uid": "18739960-1f9a48e8-e1bf-41a8-9a0f-fe97c489c85e"
	},
	"item": [
		{
			"name": "Login",
			"id": "f89da9bc-7e5a-4263-836b-818d102ef17b",
			"protocolProfileBehavior": {
				"disableBodyPruning": true
			},
			"request": {
				"auth": {
					"type": "basic",
					"basic": [
						{
							"key": "password",
							"value": "",
							"type": "string"
						},
						{
							"key": "username",
							"value": "",
							"type": "string"
						}
					]
				},
				"method": "POST",
				"header": [],
				"body": {
					"mode": "urlencoded",
					"urlencoded": [
						{
							"key": "email",
							"value": "someone@email.com",
							"type": "text"
						},
						{
							"key": "password",
							"value": "securepassword",
							"type": "text"
						}
					]
				},
				"url": {
					"raw": "{{host}}/auth/login",
					"host": [
						"{{host}}"
					],
					"path": [
						"auth",
						"login"
					]
				}
			},
			"response": []
		},
		{
			"name": "Register",
			"id": "530854e8-898d-499b-a2ca-c55e7b4e6266",
			"protocolProfileBehavior": {
				"disableBodyPruning": true
			},
			"request": {
				"method": "POST",
				"header": [],
				"body": {
					"mode": "urlencoded",
					"urlencoded": [
						{
							"key": "email",
							"value": "someone@email.com",
							"type": "text"
						},
						{
							"key": "password",
							"value": "securepassword",
							"type": "text"
						}
					]
				},
				"url": {
					"raw": "{{host}}/auth/register",
					"host": [
						"{{host}}"
					],
					"path": [
						"auth",
						"register"
					]
				}
			},
			"response": []
		},
		{
			"name": "WhoaAmI",
			"id": "83912a35-7281-4f46-b161-7f1a683b97df",
			"protocolProfileBehavior": {
				"disableBodyPruning": true
			},
			"request": {
				"method": "GET",
				"header": [],
				"url": {
					"raw": "{{host}}/auth/whoami",
					"host": [
						"{{host}}"
					],
					"path": [
						"auth",
						"whoami"
					]
				}
			},
			"response": []
		},
		{
			"name": "Logout",
			"id": "5e956ad3-d989-4786-9557-80ef5040a581",
			"protocolProfileBehavior": {
				"disableBodyPruning": true
			},
			"request": {
				"method": "GET",
				"header": [],
				"url": {
					"raw": "{{host}}/auth/logout",
					"host": [
						"{{host}}"
					],
					"path": [
						"auth",
						"logout"
					]
				}
			},
			"response": []
		}
	]
}